README.rst
setup.py
simlord/simlord.py
simlord/test_cigar.py
simlord/version.py
simlord.egg-info/PKG-INFO
simlord.egg-info/SOURCES.txt
simlord.egg-info/dependency_links.txt
simlord.egg-info/entry_points.txt
simlord.egg-info/not-zip-safe
simlord.egg-info/requires.txt
simlord.egg-info/top_level.txt