Metadata-Version: 1.1
Name: simlord
Version: 1.0.3
Summary: SimLoRD is a read simulator for long reads from third generation sequencing and is currently focused on the Pacific Biosciences SMRT error model.
Home-page: https://bitbucket.org/genomeinformatics/simlord/
Author: Bianca Stöcker
Author-email: bianca.stoecker@uni-due.de
License: MIT
Platform: UNKNOWN
Classifier: Development Status :: 5 - Production/Stable
Classifier: Environment :: Console
Classifier: Intended Audience :: Science/Research
Classifier: License :: OSI Approved :: MIT License
Classifier: Natural Language :: English
Classifier: Programming Language :: Python :: 3
Classifier: Topic :: Scientific/Engineering :: Bio-Informatics
